mcbews/case.py
mcbews/chat.py
mcbews/context.py
mcbews/minecraft_output.py
mcbews/minecraft_properties.py
mcbews/ws.py
mcbews-0.0.1b10.dist-info/METADATA
mcbews-0.0.1b10.dist-info/WHEEL
mcbews-0.0.1b10.dist-info/top_level.txt
mcbews-0.0.1b10.dist-info/RECORD
