Metadata-Version: 2.1
Name: mcbews
Version: 0.0.1b10
Summary: A Bot for Minecraft: Bedrock Edition programmed in python using websocket
Home-page: UNKNOWN
Author: phoenixR
License: MIT
Platform: UNKNOWN
Requires-Dist: websockets
